80un-0.2.3.dist-info/licenses/LICENSE
un80/__init__.py
un80/arc.py
un80/bas.py
un80/cli.py
un80/cpm.py
un80/crlzh.py
un80/crunch.py
un80/lbr.py
un80/squeeze.py
80un-0.2.3.dist-info/METADATA
80un-0.2.3.dist-info/WHEEL
80un-0.2.3.dist-info/entry_points.txt
80un-0.2.3.dist-info/top_level.txt
80un-0.2.3.dist-info/RECORD
