Metadata-Version: 2.4
Name: 80un
Version: 0.2.3
Summary: Unpacker for CP/M compression and packing formats
Author: avwohl
License-Expression: GPL-3.0-or-later
Project-URL: Homepage, https://github.com/avwohl/80un
Project-URL: Repository, https://github.com/avwohl/80un
Keywords: cpm,cp/m,8080,unpack,squeeze,crunch,lbr,arc,retro
Classifier: Development Status :: 3 - Alpha
Classifier: Environment :: Console
Classifier: Intended Audience :: Developers
Classifier: Operating System :: OS Independent
Classifier: Programming Language :: Python :: 3
Classifier: Programming Language :: Python :: 3.8
Classifier: Programming Language :: Python :: 3.9
Classifier: Programming Language :: Python :: 3.10
Classifier: Programming Language :: Python :: 3.11
Classifier: Programming Language :: Python :: 3.12
Classifier: Topic :: System :: Archiving :: Compression
Classifier: Topic :: System :: Archiving
Requires-Python: >=3.8
License-File: LICENSE
Provides-Extra: dev
Requires-Dist: pytest; extra == "dev"
Requires-Dist: pytest-cov; extra == "dev"
Dynamic: license-file
